{"v":"5.7.5","fr":100,"ip":0,"op":500,"w":1080,"h":1920,"nm":"Comp 1","ddd":0,"assets":[],"layers":[{"ddd":0,"ind":0,"ty":3,"nm":"","sr":1,"ks":{"o":{"a":0,"k":100,"ix":2},"r":{"a":0,"k":0,"ix":2},"p":{"a":0,"k":[1042,83],"ix":2},"a":{"a":0,"k":[0,0],"ix":2},"s":{"a":0,"k":[100,100],"ix":2}},"ao":0,"ip":0,"op":500,"st":0,"bm":0,"hd":false},{"ddd":0,"ind":1,"ty":4,"nm":"SmallestCircle","sr":1,"ks":{"o":{"a":0,"k":100,"ix":2},"r":{"a":0,"k":0,"ix":2},"p":{"a":0,"k":[0,0],"ix":2},"a":{"a":0,"k":[0,0],"ix":2},"s":{"a":0,"k":[100,100],"ix":2}},"ao":0,"hd":false,"parent":0,"shapes":[{"ty":"gr","hd":false,"it":[{"ty":"el","hd":false,"d":1,"s":{"a":0,"k":[335.1056677903542,335.1056677903543],"ix":2},"p":{"a":0,"k":[0,0],"ix":2}},{"ty":"fl","c":{"a":0,"k":[1,0.8392156862745098,0.25098039215686274],"ix":2},"o":{"a":0,"k":0,"ix":2},"r":1,"bm":0,"nm":"Fill 1","mn":"ADBE Vector Graphic - Fill","hd":false},{"ty":"st","c":{"a":0,"k":[0.8980392156862745,0.6196078431372549,0.42745098039215684],"ix":2},"o":{"a":0,"k":100,"ix":2},"w":{"a":0,"k":10,"ix":2},"hd":false,"lc":2,"lj":2},{"ty":"tm","s":{"a":0,"k":25,"ix":2},"e":{"a":0,"k":100,"ix":2},"o":{"a":0,"k":180,"ix":2},"m":1,"hd":false},{"ty":"tr","hd":false,"p":{"a":0,"k":[0,0],"ix":2},"a":{"a":0,"k":[0,0],"ix":2},"s":{"a":0,"k":[100,100],"ix":2},"r":{"a":1,"k":[{"t":0,"s":[0],"i":{"x":[1],"y":[1]},"o":{"x":[0],"y":[0]}},{"t":166,"s":[360],"i":{"x":[1],"y":[1]},"o":{"x":[0],"y":[0]}},{"t":320,"s":[720],"i":{"x":[1],"y":[1]},"o":{"x":[0],"y":[0]}},{"t":500,"s":[1080],"i":{"x":[1],"y":[1]},"o":{"x":[0],"y":[0]}}],"ix":2},"o":{"a":0,"k":100,"ix":2},"sk":{"a":0,"k":0,"ix":2},"sa":{"a":0,"k":0,"ix":2}}]}],"ip":0,"op":500,"st":0,"bm":0},{"ddd":0,"ind":2,"ty":4,"nm":"MediumCirlce","sr":1,"ks":{"o":{"a":0,"k":100,"ix":2},"r":{"a":0,"k":0,"ix":2},"p":{"a":0,"k":[0,0],"ix":2},"a":{"a":0,"k":[0,0],"ix":2},"s":{"a":0,"k":[100,100],"ix":2}},"ao":0,"hd":false,"parent":0,"shapes":[{"ty":"gr","hd":false,"it":[{"ty":"el","hd":false,"d":1,"s":{"a":0,"k":[549.3338494076255,549.3338494076256],"ix":2},"p":{"a":0,"k":[0,0],"ix":2}},{"ty":"fl","c":{"a":0,"k":[1,0.8392156862745098,0.25098039215686274],"ix":2},"o":{"a":0,"k":0,"ix":2},"r":1,"bm":0,"nm":"Fill 1","mn":"ADBE Vector Graphic - Fill","hd":false},{"ty":"st","c":{"a":0,"k":[0.8980392156862745,0.6196078431372549,0.42745098039215684],"ix":2},"o":{"a":0,"k":100,"ix":2},"w":{"a":0,"k":10,"ix":2},"hd":false,"lc":2,"lj":2},{"ty":"tm","s":{"a":0,"k":0,"ix":2},"e":{"a":0,"k":100,"ix":2},"o":{"a":0,"k":0,"ix":2},"m":1,"hd":false},{"ty":"tr","hd":false,"p":{"a":0,"k":[0,0],"ix":2},"a":{"a":0,"k":[0,0],"ix":2},"s":{"a":0,"k":[100,100],"ix":2},"r":{"a":1,"k":[{"t":0,"s":[0],"i":{"x":[1],"y":[1]},"o":{"x":[0],"y":[0]}},{"t":250,"s":[360],"i":{"x":[1],"y":[1]},"o":{"x":[0],"y":[0]}},{"t":500,"s":[720],"i":{"x":[1],"y":[1]},"o":{"x":[0],"y":[0]}}],"ix":2},"o":{"a":0,"k":100,"ix":2},"sk":{"a":0,"k":0,"ix":2},"sa":{"a":0,"k":0,"ix":2}}]}],"ip":0,"op":500,"st":0,"bm":0},{"ddd":0,"ind":3,"ty":4,"nm":"BigCirle","sr":1,"ks":{"o":{"a":0,"k":100,"ix":2},"r":{"a":0,"k":0,"ix":2},"p":{"a":0,"k":[0,0],"ix":2},"a":{"a":0,"k":[0,0],"ix":2},"s":{"a":0,"k":[100,100],"ix":2}},"ao":0,"hd":false,"parent":0,"shapes":[{"ty":"gr","hd":false,"it":[{"ty":"el","hd":false,"d":1,"s":{"a":0,"k":[818.4467581285522,818.4467581285523],"ix":2},"p":{"a":0,"k":[0,0],"ix":2}},{"ty":"fl","c":{"a":0,"k":[1,0.8392156862745098,0.25098039215686274],"ix":2},"o":{"a":0,"k":0,"ix":2},"r":1,"bm":0,"nm":"Fill 1","mn":"ADBE Vector Graphic - Fill","hd":false},{"ty":"st","c":{"a":0,"k":[0.8980392156862745,0.6196078431372549,0.42745098039215684],"ix":2},"o":{"a":0,"k":100,"ix":2},"w":{"a":0,"k":10,"ix":2},"hd":false,"lc":2,"lj":2},{"ty":"tm","s":{"a":0,"k":25,"ix":2},"e":{"a":0,"k":100,"ix":2},"o":{"a":0,"k":0,"ix":2},"m":1,"hd":false},{"ty":"tr","hd":false,"p":{"a":0,"k":[0,0],"ix":2},"a":{"a":0,"k":[0,0],"ix":2},"s":{"a":0,"k":[100,100],"ix":2},"r":{"a":1,"k":[{"t":0,"s":[0],"i":{"x":[1],"y":[1]},"o":{"x":[0],"y":[0]}},{"t":500,"s":[-360],"i":{"x":[1],"y":[1]},"o":{"x":[0],"y":[0]}}],"ix":2},"o":{"a":0,"k":100,"ix":2},"sk":{"a":0,"k":0,"ix":2},"sa":{"a":0,"k":0,"ix":2}}]}],"ip":0,"op":500,"st":0,"bm":0},{"ddd":0,"ind":4,"ty":3,"nm":"","sr":1,"ks":{"o":{"a":0,"k":100,"ix":2},"r":{"a":0,"k":0,"ix":2},"p":{"a":0,"k":[86,1851],"ix":2},"a":{"a":0,"k":[0,0],"ix":2},"s":{"a":0,"k":[100,100],"ix":2}},"ao":0,"ip":0,"op":500,"st":0,"bm":0,"hd":false},{"ddd":0,"ind":5,"ty":4,"nm":"SmallestCircle","sr":1,"ks":{"o":{"a":0,"k":100,"ix":2},"r":{"a":0,"k":0,"ix":2},"p":{"a":0,"k":[0,0],"ix":2},"a":{"a":0,"k":[0,0],"ix":2},"s":{"a":0,"k":[100,100],"ix":2}},"ao":0,"hd":false,"parent":4,"shapes":[{"ty":"gr","hd":false,"it":[{"ty":"el","hd":false,"d":1,"s":{"a":0,"k":[335.1056677903542,335.1056677903543],"ix":2},"p":{"a":0,"k":[0,0],"ix":2}},{"ty":"fl","c":{"a":0,"k":[1,0.8392156862745098,0.25098039215686274],"ix":2},"o":{"a":0,"k":0,"ix":2},"r":1,"bm":0,"nm":"Fill 1","mn":"ADBE Vector Graphic - Fill","hd":false},{"ty":"st","c":{"a":0,"k":[0.8980392156862745,0.6196078431372549,0.42745098039215684],"ix":2},"o":{"a":0,"k":100,"ix":2},"w":{"a":0,"k":10,"ix":2},"hd":false,"lc":2,"lj":2},{"ty":"tm","s":{"a":0,"k":25,"ix":2},"e":{"a":0,"k":100,"ix":2},"o":{"a":0,"k":180,"ix":2},"m":1,"hd":false},{"ty":"tr","hd":false,"p":{"a":0,"k":[0,0],"ix":2},"a":{"a":0,"k":[0,0],"ix":2},"s":{"a":0,"k":[100,100],"ix":2},"r":{"a":1,"k":[{"t":0,"s":[0],"i":{"x":[1],"y":[1]},"o":{"x":[0],"y":[0]}},{"t":166,"s":[360],"i":{"x":[1],"y":[1]},"o":{"x":[0],"y":[0]}},{"t":320,"s":[720],"i":{"x":[1],"y":[1]},"o":{"x":[0],"y":[0]}},{"t":500,"s":[1000],"i":{"x":[1],"y":[1]},"o":{"x":[0],"y":[0]}}],"ix":2},"o":{"a":0,"k":100,"ix":2},"sk":{"a":0,"k":0,"ix":2},"sa":{"a":0,"k":0,"ix":2}}]}],"ip":0,"op":500,"st":0,"bm":0},{"ddd":0,"ind":6,"ty":4,"nm":"MediumCirlce","sr":1,"ks":{"o":{"a":0,"k":100,"ix":2},"r":{"a":0,"k":0,"ix":2},"p":{"a":0,"k":[0,0],"ix":2},"a":{"a":0,"k":[0,0],"ix":2},"s":{"a":0,"k":[100,100],"ix":2}},"ao":0,"hd":false,"parent":4,"shapes":[{"ty":"gr","hd":false,"it":[{"ty":"el","hd":false,"d":1,"s":{"a":0,"k":[549.3338494076255,549.3338494076256],"ix":2},"p":{"a":0,"k":[0,0],"ix":2}},{"ty":"fl","c":{"a":0,"k":[1,0.8392156862745098,0.25098039215686274],"ix":2},"o":{"a":0,"k":0,"ix":2},"r":1,"bm":0,"nm":"Fill 1","mn":"ADBE Vector Graphic - Fill","hd":false},{"ty":"st","c":{"a":0,"k":[0.8980392156862745,0.6196078431372549,0.42745098039215684],"ix":2},"o":{"a":0,"k":100,"ix":2},"w":{"a":0,"k":10,"ix":2},"hd":false,"lc":2,"lj":2},{"ty":"tm","s":{"a":0,"k":0,"ix":2},"e":{"a":0,"k":75,"ix":2},"o":{"a":0,"k":0,"ix":2},"m":1,"hd":false},{"ty":"tr","hd":false,"p":{"a":0,"k":[0,0],"ix":2},"a":{"a":0,"k":[0,0],"ix":2},"s":{"a":0,"k":[100,100],"ix":2},"r":{"a":1,"k":[{"t":0,"s":[0],"i":{"x":[1],"y":[1]},"o":{"x":[0],"y":[0]}},{"t":250,"s":[360],"i":{"x":[1],"y":[1]},"o":{"x":[0],"y":[0]}},{"t":500,"s":[720],"i":{"x":[1],"y":[1]},"o":{"x":[0],"y":[0]}}],"ix":2},"o":{"a":0,"k":100,"ix":2},"sk":{"a":0,"k":0,"ix":2},"sa":{"a":0,"k":0,"ix":2}}]}],"ip":0,"op":500,"st":0,"bm":0},{"ddd":0,"ind":7,"ty":4,"nm":"BigCirle","sr":1,"ks":{"o":{"a":0,"k":100,"ix":2},"r":{"a":0,"k":0,"ix":2},"p":{"a":0,"k":[0,0],"ix":2},"a":{"a":0,"k":[0,0],"ix":2},"s":{"a":0,"k":[100,100],"ix":2}},"ao":0,"hd":false,"parent":4,"shapes":[{"ty":"gr","hd":false,"it":[{"ty":"el","hd":false,"d":1,"s":{"a":0,"k":[818.4467581285522,818.4467581285523],"ix":2},"p":{"a":0,"k":[0,0],"ix":2}},{"ty":"fl","c":{"a":0,"k":[1,0.8392156862745098,0.25098039215686274],"ix":2},"o":{"a":0,"k":0,"ix":2},"r":1,"bm":0,"nm":"Fill 1","mn":"ADBE Vector Graphic - Fill","hd":false},{"ty":"st","c":{"a":0,"k":[0.8980392156862745,0.6196078431372549,0.42745098039215684],"ix":2},"o":{"a":0,"k":100,"ix":2},"w":{"a":0,"k":10,"ix":2},"hd":false,"lc":2,"lj":2},{"ty":"tm","s":{"a":0,"k":25,"ix":2},"e":{"a":0,"k":100,"ix":2},"o":{"a":0,"k":0,"ix":2},"m":1,"hd":false},{"ty":"tr","hd":false,"p":{"a":0,"k":[0,0],"ix":2},"a":{"a":0,"k":[0,0],"ix":2},"s":{"a":0,"k":[100,100],"ix":2},"r":{"a":1,"k":[{"t":0,"s":[0],"i":{"x":[1],"y":[1]},"o":{"x":[0],"y":[0]}},{"t":500,"s":[-360],"i":{"x":[1],"y":[1]},"o":{"x":[0],"y":[0]}}],"ix":2},"o":{"a":0,"k":100,"ix":2},"sk":{"a":0,"k":0,"ix":2},"sa":{"a":0,"k":0,"ix":2}}]}],"ip":0,"op":500,"st":0,"bm":0}],"markers":[]}